tfinance/__init__.py
tfinance/market.py
tfinance/ticker.py
tfinance/tse_scrapper.py
tfinance/abc/base_scrapper.py
tfinance/meta/singleton_meta.py
tfinance/models/__init__.py
tfinance/models/meta.py
tfinance/models/sector_model.py
tfinance/models/ticker_history_mixin.py
tfinance/models/ticker_model.py
tfinance-0.1.4.dist-info/LICENSE
tfinance-0.1.4.dist-info/METADATA
tfinance-0.1.4.dist-info/WHEEL
tfinance-0.1.4.dist-info/top_level.txt
tfinance-0.1.4.dist-info/RECORD
