Metadata-Version: 2.1
Name: tfinance
Version: 0.1.4
Summary: Tehran Stock Exchange OSINT Tool for Python
Home-page: https://github.com/sadeg/tfinance
Author: Sadiq Rahmati
Author-email: sadeg.r@protonmail.com
License: GPL3
Platform: UNKNOWN
License-File: LICENSE
Requires-Dist: bs4
Requires-Dist: lxml
Requires-Dist: pandas
Requires-Dist: requests
Requires-Dist: sqlalchemy
Requires-Dist: tqdm
